PrizePick_Wrapper/CustomExceptions.py
PrizePick_Wrapper/PrizePicks.py
PrizePick_Wrapper/__init__.py
PrizePick_Wrapper-0.2.0.dist-info/METADATA
PrizePick_Wrapper-0.2.0.dist-info/WHEEL
PrizePick_Wrapper-0.2.0.dist-info/top_level.txt
PrizePick_Wrapper-0.2.0.dist-info/RECORD
