Metadata-Version: 2.1
Name: PrizePick-Wrapper
Version: 0.2.0
Summary: PrizePick Wrapper to easily access the PrizePick API
Requires-Dist: certifi ==2024.12.14
Requires-Dist: charset-normalizer ==2.0.10
Requires-Dist: idna ==3.3
Requires-Dist: requests ==2.26.0
Requires-Dist: urllib3 ==1.26.7
